ievv_auth/__init__.py
ievv_auth/version.json
ievv_auth/ievv_api_key/README.md
ievv_auth/ievv_api_key/__init__.py
ievv_auth/ievv_api_key/admin.py
ievv_auth/ievv_api_key/apps.py
ievv_auth/ievv_api_key/models.py
ievv_auth/ievv_api_key/views.py
ievv_auth/ievv_api_key/management/__init__.py
ievv_auth/ievv_api_key/management/commands/__init__.py
ievv_auth/ievv_api_key/migrations/0001_initial.py
ievv_auth/ievv_api_key/migrations/0002_auto_20201119_1956.py
ievv_auth/ievv_api_key/migrations/__init__.py
ievv_auth/ievv_api_key/tests/__init__.py
ievv_auth/ievv_api_key/tests/test_models.py
ievv_auth/ievv_jwt/README.md
ievv_auth/ievv_jwt/__init__.py
ievv_auth/ievv_jwt/admin.py
ievv_auth/ievv_jwt/apps.py
ievv_auth/ievv_jwt/exceptions.py
ievv_auth/ievv_jwt/models.py
ievv_auth/ievv_jwt/settings.py
ievv_auth/ievv_jwt/views.py
ievv_auth/ievv_jwt/api/__init__.py
ievv_auth/ievv_jwt/api/authentication.py
ievv_auth/ievv_jwt/api/serializers/__init__.py
ievv_auth/ievv_jwt/api/serializers/api_key_serializers.py
ievv_auth/ievv_jwt/api/views/__init__.py
ievv_auth/ievv_jwt/api/views/api_key_views.py
ievv_auth/ievv_jwt/api/views/base_view.py
ievv_auth/ievv_jwt/backends/__init__.py
ievv_auth/ievv_jwt/backends/api_key_backend.py
ievv_auth/ievv_jwt/backends/backend_registry.py
ievv_auth/ievv_jwt/backends/base_backend.py
ievv_auth/ievv_jwt/migrations/__init__.py
ievv_auth/ievv_jwt/tests/__init__.py
ievv_auth/ievv_jwt/tests/test_utils.py
ievv_auth/ievv_jwt/tests/test_api/__init__.py
ievv_auth/ievv_jwt/tests/test_api/api_test_mixin.py
ievv_auth/ievv_jwt/tests/test_api/test_api_key_views.py
ievv_auth/ievv_jwt/tests/test_backends/__init__.py
ievv_auth/ievv_jwt/tests/test_backends/test_api_key_backend.py
ievv_auth/ievv_jwt/tests/test_backends/test_backend_registry.py
ievv_auth/ievv_jwt/tests/test_backends/test_base_backend.py
ievv_auth/ievv_jwt/utils/__init__.py
ievv_auth/ievv_jwt/utils/deep_merge.py
ievv_auth/ievv_jwt/utils/load_settings.py
ievv_auth/project/__init__.py
ievv_auth-2.0.1.dist-info/LICENSE
ievv_auth-2.0.1.dist-info/METADATA
ievv_auth-2.0.1.dist-info/WHEEL
ievv_auth-2.0.1.dist-info/top_level.txt
ievv_auth-2.0.1.dist-info/RECORD
