Metadata-Version: 2.1
Name: ievv-auth
Version: 2.0.1
Summary: Authentication modules for the Django framework.
Home-page: https://github.com/appressoas/ievv_auth
Author: Appresso developers
Author-email: post@appresso.no
License: BSD
Platform: UNKNOWN
Classifier: Development Status :: 4 - Beta
Classifier: Environment :: Web Environment
Classifier: Framework :: Django
Classifier: Intended Audience :: Developers
Classifier: License :: OSI Approved
Classifier: Operating System :: OS Independent
Classifier: Programming Language :: Python
Requires-Dist: Django (>=3)
Requires-Dist: PyJWT (>=1.7.1)
Requires-Dist: djangorestframework
Requires-Dist: psycopg2
Requires-Dist: django-ipware
